README.md
setup.cfg
setup.py
cloudgenix_get_all_interface_info/__init__.py
cloudgenix_get_all_interface_info.egg-info/PKG-INFO
cloudgenix_get_all_interface_info.egg-info/SOURCES.txt
cloudgenix_get_all_interface_info.egg-info/dependency_links.txt
cloudgenix_get_all_interface_info.egg-info/entry_points.txt
cloudgenix_get_all_interface_info.egg-info/requires.txt
cloudgenix_get_all_interface_info.egg-info/top_level.txt